ui/__init__.py
ui/tests/__init__.py
ui/tests/conftest.py
ui/tests/test_ui.py
python_cli_ui-0.7.5.dist-info/LICENSE
python_cli_ui-0.7.5.dist-info/METADATA
python_cli_ui-0.7.5.dist-info/WHEEL
python_cli_ui-0.7.5.dist-info/top_level.txt
python_cli_ui-0.7.5.dist-info/RECORD
