Metadata-Version: 2.1
Name: python-cli-ui
Version: 0.7.5
Summary: Build Nice User Interfaces In The Terminal
Home-page: https://github.com/TankerHQ/python-cli-ui
Author: Dimitri Merejkowsky
License: UNKNOWN
Platform: UNKNOWN
Classifier: Programming Language :: Python :: 3.4
Classifier: Programming Language :: Python :: 3.5
Classifier: Programming Language :: Python :: 3.6
Classifier: Programming Language :: Python :: 3.7
Requires-Dist: colorama
Requires-Dist: tabulate
Requires-Dist: unidecode
Provides-Extra: dev
Requires-Dist: sphinx ; extra == 'dev'
Requires-Dist: ghp-import ; extra == 'dev'
Requires-Dist: pytest ; extra == 'dev'
Requires-Dist: pyflakes ; extra == 'dev'
